{
  "nombre": "Inicio de Sesion",
  "query": "false",
  "clave_primaria": "false",
  "identificador": "Login",
  "estructura": "1x2",
  "campos": [
    {
      "name": "usuario",
      "type": "text",
      "id": "usuario",
      "label": "Usuario",
      "placeholder": "Usuario",
      "eventos": {
        "obligatorio": {
          "mensaje": "Debe ingresar su usuario"
        }
      }
    },
    {
      "name": "clave",
      "id": "clave",
      "type": "password",
      "label": "Clave",
      "placeholder": "Clave",
      "eventos": {
        "obligatorio": {
          "mensaje": "Debe ingresar su clave"
        }
      }
    }
  ]
}
