{
  "nombre": "Menu Test",
  "id": "menu-1",
  "class": "nav nav-aside menu short-menu",
  "items": {
    "item1": {
      "id": "item-administracion",
      "class": "li-parent",
      "label": "<span class=\"fa fa-wrench\"></span> <span>Menu Principal</span>",
      "url": "#",
      "encode_html": false,
      "submenu": {
        "id": "",
        "class": "",
        "items": {
          "1": {
            "id": "",
            "class": "",
            "label": "<span class=\"fa fa-users\"></span> <span class=\"inner-text\">Sub Nivel-1</span>",
            "url": "/jadmin/clientes/",
            "encode_html": false,
            "submenu": {
              "id": "",
              "class": "",
              "items": {
                "1": {
                  "id": "",
                  "class": "",
                  "label": "Nivel 2",
                  "url": "#",
                  "encode_html": false
                },
                "2": {
                  "id": "",
                  "class": "",
                  "label": "&copy; Jida Desarrollos",
                  "url": "#",
                  "encode_html": true
                }
              }
            }
          }
        }
      }
    }
  }
}